setup.py
zfx/__init__.py
zfx/a模块.py
zfx/office_excel.py
zfx/zmodule_240414A.py
zfx/zprint.py
zfx/抛出异常.py
zfx/数据库_mysql.py
zfx/文件_删除文件.py
zfx/文件_取大小B.py
zfx/文件_取大小GB.py
zfx/文件_取大小KB.py
zfx/文件_取大小MB.py
zfx/文件_复制.py
zfx/文件_封装Py代码成EXE_普通编译.py
zfx/文件_封装Py代码成EXE_独立编译.py
zfx/文件_文件是否存在.py
zfx/文件_枚举.py
zfx/文本文件_写入文件内容.py
zfx/文本文件_取指定文件文本行数.py
zfx/文本文件_读入全部内容.py
zfx/目录_创建.py
zfx/目录_取运行目录.py
zfx/算数_保留小数点后指定位数.py
zfx/算数_取绝对值.py
zfx/算数_向上取整.py
zfx/算数_向下取整.py
zfx/算数_四舍五入.py
zfx/算数_求余弦.py
zfx/算数_求余数.py
zfx/算数_求反正切.py
zfx/算数_求平方根.py
zfx/算数_求次方.py
zfx/算数_求正切.py
zfx/算数_求正弦.py
zfx/系统_取CPU型号.py
zfx/系统_取剪辑版内容.py
zfx/系统_取操作系统类别.py
zfx/系统_取时区.py
zfx/系统_取用户名.py
zfx/系统_取硬盘特征字.py
zfx/系统_取系统现行时间.py
zfx/系统_强制关机.py
zfx/系统_强制注销.py
zfx/系统_强制重启.py
zfx/系统_是否为管理员.py
zfx/系统_是否已联网.py
zfx/系统_清空回收站.py
zfx/系统_生成随机mac.py
zfx/系统_置剪辑版内容.py
zfx/系统任务计划_创建.py
zfx/系统任务计划_删除.py
zfx/系统任务计划_遍历名称.py
zfx/线程_取当前线程名称.py
zfx/线程_取当前线程对象.py
zfx/线程_取当前线程标识符.py
zfx/编码_BASE64编码.py
zfx/编码_BASE64解码.py
zfx/编码_UTF8编码.py
zfx/编码_UTF8解码.py
zfx/编码_十六进制文本到字符串.py
zfx/编码_字符串到十六进制文本.py
zfx/网页协议.py
zfx/谷歌填表.py
zfx/进程_名取ID.py
zfx/邮件pop3.py
zfx/配置文件_写配置项.py
zfx/配置文件_读配置项.py
zfxtest.egg-info/PKG-INFO
zfxtest.egg-info/SOURCES.txt
zfxtest.egg-info/dependency_links.txt
zfxtest.egg-info/requires.txt
zfxtest.egg-info/top_level.txt